sports_news_collector/__init__.py
sports_news_collector/email_sender.py
sports_news_collector/news_crawler.py
sports_news_collector/sports_news_collector.py
sports_news_collector-0.1.dist-info/METADATA
sports_news_collector-0.1.dist-info/WHEEL
sports_news_collector-0.1.dist-info/top_level.txt
sports_news_collector-0.1.dist-info/RECORD
