Metadata-Version: 2.1
Name: sports-news-collector
Version: 0.1
Summary: Provide services by collecting various sports news
Home-page: https://github.com/hasangchun/sports_news_collector
Author: Sangchun Ha
Author-email: seomk9896@naver.com
License: UNKNOWN
Platform: UNKNOWN
Classifier: Programming Language :: Python :: 3
Classifier: Programming Language :: Python :: 3.2
Classifier: Programming Language :: Python :: 3.3
Classifier: Programming Language :: Python :: 3.4
Classifier: Programming Language :: Python :: 3.5
Classifier: Programming Language :: Python :: 3.6
Classifier: Programming Language :: Python :: 3.7
Classifier: Programming Language :: Python :: 3.8
Requires-Python: >=3
Requires-Dist: beautifulsoup4
Requires-Dist: requests
Requires-Dist: pretty-html-table
Requires-Dist: pandas
Requires-Dist: pororo
